{
  "resourceType": "Bundle",
  "entry": [
    {
      "resource": {
        "resourceType": "MedicationPrescription",
        "id": "109",
        "contained": [
          {
            "resourceType": "Medication",
            "id": "med",
            "name": "Estrogens, Conjugated (USP) 0.625 MG Oral Tablet [Premarin]",
            "code": {
              "coding": [
                {
                  "system": "http://www.nlm.nih.gov/research/umls/rxnorm",
                  "code": "150840",
                  "display": "Estrogens, Conjugated (USP) 0.625 MG Oral Tablet [Premarin]"
                }
              ]
            }
          }
        ],
        "medication": {
          "reference": "#med"
        }
      }
    }
  ]
}